squlearn/__init__.py
squlearn/encoding_circuit/__init__.py
squlearn/encoding_circuit/encoding_circuit_base.py
squlearn/encoding_circuit/encoding_circuit_derivatives.py
squlearn/encoding_circuit/layered_encoding_circuit.py
squlearn/encoding_circuit/pruned_encoding_circuit.py
squlearn/encoding_circuit/transpiled_encoding_circuit.py
squlearn/encoding_circuit/circuit_library/__init__.py
squlearn/encoding_circuit/circuit_library/chebyshev_pqc.py
squlearn/encoding_circuit/circuit_library/chebyshev_rx.py
squlearn/encoding_circuit/circuit_library/chebyshev_tower.py
squlearn/encoding_circuit/circuit_library/highdim_encoding_circuit.py
squlearn/encoding_circuit/circuit_library/hubregtsen_encoding_circuit.py
squlearn/encoding_circuit/circuit_library/kyriienko_nonlinear_encoding_circuit.py
squlearn/encoding_circuit/circuit_library/multi_control_encoding_circuit.py
squlearn/encoding_circuit/circuit_library/param_z_feature_map.py
squlearn/encoding_circuit/circuit_library/qcnn_encoding_circuit.py
squlearn/encoding_circuit/circuit_library/qiskit_encoding_circuit.py
squlearn/encoding_circuit/circuit_library/random_encoding_circuit.py
squlearn/encoding_circuit/circuit_library/random_layered_encoding_circuit.py
squlearn/encoding_circuit/circuit_library/yz_cx_encoding_circuit.py
squlearn/kernel/__init__.py
squlearn/kernel/qgpc.py
squlearn/kernel/qgpr.py
squlearn/kernel/qkode.py
squlearn/kernel/qkrr.py
squlearn/kernel/qsvc.py
squlearn/kernel/qsvr.py
squlearn/kernel/loss/__init__.py
squlearn/kernel/loss/kernel_loss_base.py
squlearn/kernel/loss/negative_log_likelihood.py
squlearn/kernel/loss/ode_loss.py
squlearn/kernel/loss/target_alignment.py
squlearn/kernel/lowlevel_kernel/__init__.py
squlearn/kernel/lowlevel_kernel/fidelity_kernel.py
squlearn/kernel/lowlevel_kernel/fidelity_kernel_expectation_value.py
squlearn/kernel/lowlevel_kernel/fidelity_kernel_statevector.py
squlearn/kernel/lowlevel_kernel/kernel_matrix_base.py
squlearn/kernel/lowlevel_kernel/kernel_optimizer.py
squlearn-0.10.0.dist-info/licenses/LICENSE.txt
squlearn-0.10.0.dist-info/WHEEL
squlearn-0.10.0.dist-info/METADATA
squlearn-0.10.0.dist-info/RECORD
