Metadata-Version: 2.4
Name: squlearn
Version: 0.10.0
Summary: A library for quantum machine learning following the scikit-learn standard.
Keywords: quantum,machine learning,qml
Author-email: David Kreplin <david.kreplin@ipa.fraunhofer.de>, Moritz Willmann <moritz.willmann@ipa.fraunhofer.de>, Jan Schnabel <jan.schnabel@ipa.fraunhofer.de>, Frederic Rapp <frederic.rapp@ipa.fraunhofer.de>, Manuel Hagelüken <manuel.hagelueken@ipa.fraunhofer.de>, Marco Roth <marco.roth@ipa.fraunhofer.de>
Maintainer-email: David Kreplin <david.kreplin@ipa.fraunhofer.de>, Moritz Willmann <moritz.willmann@ipa.fraunhofer.de>
Requires-Python: >=3.9
Classifier: License :: OSI Approved :: Apache Software License
Classifier: Programming Language :: Python
Classifier: Programming Language :: Python :: 3
License-File: LICENSE.txt
Requires-Dist: bayesian-optimization>=1.4.3,<2
Requires-Dist: dill>=0.3.5
Requires-Dist: mapomatic>=0.10.0
Requires-Dist: networkx>=3.0
Requires-Dist: numpy>=1.20
Requires-Dist: pennylane>=0.34.0
Requires-Dist: qiskit>=0.45.0,<2
Requires-Dist: qiskit-aer>=0.12.0
Requires-Dist: qiskit-algorithms>=0.3.0
Requires-Dist: qiskit-ibm-runtime>=0.18.0
Requires-Dist: qiskit-machine-learning>=0.7.0
Requires-Dist: scipy>=1.8.0
Requires-Dist: scikit-learn>=1.2.0
Requires-Dist: tqdm>=4.1.0
Requires-Dist: qulacs>=0.6.0
Requires-Dist: black ; extra == "dev"
Requires-Dist: flit ; extra == "dev"
Requires-Dist: nbmake ; extra == "dev"
Requires-Dist: pylint ; extra == "dev"
Requires-Dist: pytest ; extra == "dev"
Requires-Dist: ipykernel ; extra == "docs"
Requires-Dist: jupyter-sphinx ; extra == "docs"
Requires-Dist: matplotlib>=3.4.1 ; extra == "docs"
Requires-Dist: myst-parser ; extra == "docs"
Requires-Dist: nbsphinx ; extra == "docs"
Requires-Dist: nbsphinx_link ; extra == "docs"
Requires-Dist: pylatexenc>=2.10 ; extra == "docs"
Requires-Dist: sphinx ; extra == "docs"
Requires-Dist: sphinxcontrib-spelling ; extra == "docs"
Requires-Dist: sphinx-rtd-theme<3.0.0 ; extra == "docs"
Requires-Dist: sphinx-sitemap ; extra == "docs"
Requires-Dist: scikit-learn!=1.7.1 ; extra == "docs"
Requires-Dist: jupyter ; extra == "examples"
Requires-Dist: matplotlib>=3.4.1 ; extra == "examples"
Requires-Dist: mlflow ; extra == "examples"
Requires-Dist: numpy>=1.24.1 ; extra == "examples"
Requires-Dist: pandas ; extra == "examples"
Requires-Dist: pylatexenc>=2.10 ; extra == "examples"
Requires-Dist: seaborn ; extra == "examples"
Requires-Dist: scikit-optimize ; extra == "examples"
Project-URL: documentation, https://squlearn.github.io
Project-URL: github, https://github.com/sQUlearn/squlearn
Provides-Extra: dev
Provides-Extra: docs
Provides-Extra: examples
